README.md
setup.py
pycodeexec/__init__.py
pycodeexec/asyncio.py
pycodeexec/languages.py
pycodeexec/sync.py
pycodeexec/util.py
pycodeexec.egg-info/PKG-INFO
pycodeexec.egg-info/SOURCES.txt
pycodeexec.egg-info/dependency_links.txt
pycodeexec.egg-info/requires.txt
pycodeexec.egg-info/top_level.txt