Metadata-Version: 1.0
Name: pycodeexec
Version: 0.0.2
Summary: Execute arbitrary code from a multitude of supported languages
Home-page: https://github.com/3jackdaws/pycodeexec
Author: Ian Murphy
Author-email: 3jackdaws@gmail.com
License: MIT
Platform: UNKNOWN
